flowtracker.py
setup.cfg
setup.py
flowtracker.egg-info/PKG-INFO
flowtracker.egg-info/SOURCES.txt
flowtracker.egg-info/dependency_links.txt
flowtracker.egg-info/entry_points.txt
flowtracker.egg-info/requires.txt
flowtracker.egg-info/top_level.txt