Metadata-Version: 1.1
Name: flowtracker
Version: 0.0.2
Summary: Track multi-pathed flows through Cisco Nexus switches.
Home-page: https://github.com/networktocode/flowtracker/
Author: UNKNOWN
Author-email: UNKNOWN
License: UNKNOWN
Download-URL: https://github.com/networktocode/flowtracker/tarball/0.1
Keywords: nxapi,nexus,pycsco,cisco
Platform: UNKNOWN
